[{"place_id": 275946164, "licence": "Data \u00a9 OpenStreetMap contributors, ODbL 1.0. http://osm.org/copyright", "osm_type": "way", "osm_id": 247096837, "lat": "51.5288087", "lon": "-2.570664898277388", "class": "shop", "type": "flooring;blinds;interior_decoration", "place_rank": 30, "importance": 9.99999999995449e-06, "addresstype": "shop", "name": "Trinity Transformations", "display_name": "Trinity Transformations, 81, Gloucester Road, Charlton Hayes, Patchway, South Gloucestershire, West of England, England, BS34 5JH, United Kingdom", "boundingbox": ["51.5287557", "51.5288656", "-2.5707914", "-2.5705425"]}]